LICENSE
README.md
setup.py
sugar_shell/__init__.py
sugar_shell.egg-info/PKG-INFO
sugar_shell.egg-info/SOURCES.txt
sugar_shell.egg-info/dependency_links.txt
sugar_shell.egg-info/entry_points.txt
sugar_shell.egg-info/top_level.txt